recommender/__init__.py
recommender/cli.py
recommender/core.py
simple_recommender_rg-0.1.9.dist-info/METADATA
simple_recommender_rg-0.1.9.dist-info/WHEEL
simple_recommender_rg-0.1.9.dist-info/entry_points.txt
simple_recommender_rg-0.1.9.dist-info/top_level.txt
simple_recommender_rg-0.1.9.dist-info/RECORD
