Metadata-Version: 2.4
Name: simple-recommender-rg
Version: 0.1.9
Summary: A simple content-based recommender system
Author: Rakshita Garg
License: MIT License
Classifier: License :: OSI Approved :: MIT License
Classifier: Programming Language :: Python :: 3
Requires-Python: >=3.8
Requires-Dist: pandas
Requires-Dist: scikit-learn
